metaflow_helper/__init__.py
metaflow_helper/constants.py
metaflow_helper/feature_engineer.py
metaflow_helper/modeler.py
metaflow_helper/plot.py
metaflow_helper/utils.py
metaflow_helper/models/__init__.py
metaflow_helper/models/base.py
metaflow_helper/models/keras.py
metaflow_helper/models/lightgbm.py
metaflow_helper/models/vowpalwabbit.py
metaflow_helper-0.0.1.dist-info/LICENSE
metaflow_helper-0.0.1.dist-info/METADATA
metaflow_helper-0.0.1.dist-info/WHEEL
metaflow_helper-0.0.1.dist-info/top_level.txt
metaflow_helper-0.0.1.dist-info/RECORD
