Metadata-Version: 2.1
Name: metaflow-helper
Version: 0.0.1
Summary: Convenience utilities for common machine learning tasks on Metaflow
Home-page: https://github.com/fwhigh/metaflow-helper
Author: F. William High
Author-email: fwhigh@gmail.com
License: Apache-2.0
Keywords: circleci ci cd api sdk
Platform: UNKNOWN
Classifier: Development Status :: 5 - Production/Stable
Classifier: Intended Audience :: Developers
Classifier: Intended Audience :: System Administrators
Classifier: License :: OSI Approved :: Apache Software License
Classifier: Operating System :: OS Independent
Classifier: Topic :: Software Development :: Build Tools
Classifier: Topic :: Software Development :: Libraries :: Python Modules
Classifier: Topic :: Internet
Classifier: Programming Language :: Python :: 3
Classifier: Programming Language :: Python :: 3.6
Classifier: Programming Language :: Python :: 3.7
Classifier: Programming Language :: Python :: 3.8
Classifier: Programming Language :: Python :: 3 :: Only
Requires-Python: >=3.6.0
License-File: LICENSE
Requires-Dist: tensorflow
Requires-Dist: lightgbm
Requires-Dist: vowpalwabbit
Requires-Dist: scikit-learn
Requires-Dist: numpy
Requires-Dist: plotly-express
Requires-Dist: kaleido
